[
    {
        "query": "Marlon Brando Jr. was widely considered one of the greatest and most influential ___ of all time.",
        "answer": "actors",
        "level": "1",
        "type": "cloze",
        "subject": "Marlon Brando"
    },
    {
        "query": "Marlon Brando portrayed a rebellious motorcycle gang leader named ___ in The Wild One.",
        "answer": "Johnny Strabler",
        "level": "1",
        "type": "cloze",
        "subject": "Marlon Brando"
    },
    {
        "query": "Marlon Brando Jr. was born on ___ 3, 1924.",
        "answer": "April",
        "level": "1",
        "type": "cloze",
        "subject": "Marlon Brando"
    },
    {
        "query": "Marlon Brando received his first Academy Award for Best Actor for his performance in ___",
        "answer": "On the Waterfront",
        "level": "1",
        "type": "cloze",
        "subject": "Marlon Brando"
    },
    {
        "query": "Marlon Brando portrayed Johnny Strabler in the film ___",
        "answer": "The Wild One",
        "level": "1",
        "type": "cloze",
        "subject": "Marlon Brando"
    },
    {
        "query": "Marlon Brando Jr. (April 3, 1924 \u2013 July 1, 2004) was an American ___",
        "answer": "actor",
        "level": "1",
        "type": "cloze",
        "subject": "Marlon Brando"
    },
    {
        "query": "Marlon Brando received his first Academy Award for his performance as ___ in On the Waterfront.",
        "answer": "Terry Malloy",
        "level": "1",
        "type": "cloze",
        "subject": "Marlon Brando"
    },
    {
        "query": "Marlon Brando played the role of Stanley Kowalski in ___",
        "answer": "A Streetcar Named Desire",
        "level": "1",
        "type": "cloze",
        "subject": "Marlon Brando"
    },
    {
        "query": "Marlon Brando received his first Academy Award for his performance as ___ in On the Waterfront.",
        "answer": "Terry Malloy",
        "level": "1",
        "type": "cloze",
        "subject": "Marlon Brando"
    },
    {
        "query": "Marlon Brando's portrayal of ___ in The Wild One became an emblem of the era's generational gap.",
        "answer": "Johnny Strabler",
        "level": "1",
        "type": "cloze",
        "subject": "Marlon Brando"
    },
    {
        "query": "Marlon Brando directed and starred in ___ (1961), a commercial flop.",
        "answer": "One-Eyed Jacks",
        "level": "1",
        "type": "cloze",
        "subject": "Marlon Brando"
    },
    {
        "query": "Marlon Brando starred as ___ in The Godfather (1972).",
        "answer": "Vito Corleone",
        "level": "1",
        "type": "cloze",
        "subject": "Marlon Brando"
    },
    {
        "query": "Marlon Brando played Colonel Kurtz in ___ (1979).",
        "answer": "Apocalypse Now",
        "level": "1",
        "type": "cloze",
        "subject": "Marlon Brando"
    },
    {
        "query": "Marlon Brando won his second Academy Award for his role as ___ in The Godfather.",
        "answer": "Vito Corleone",
        "level": "1",
        "type": "cloze",
        "subject": "Marlon Brando"
    },
    {
        "query": "Marlon Brando played Colonel Kurtz in ___ (1979).",
        "answer": "Apocalypse Now",
        "level": "1",
        "type": "cloze",
        "subject": "Marlon Brando"
    },
    {
        "query": "Marlon Brando starred as Vito Corleone in ___",
        "answer": "The Godfather",
        "level": "1",
        "type": "cloze",
        "subject": "Marlon Brando"
    },
    {
        "query": "Marlon Brando directed and starred in ___ (1961), a commercial flop.",
        "answer": "One-Eyed Jacks",
        "level": "1",
        "type": "cloze",
        "subject": "Marlon Brando"
    },
    {
        "query": "After a series of box-office failures, Brando won his second Academy Award for his role in ___",
        "answer": "The Godfather",
        "level": "1",
        "type": "cloze",
        "subject": "Marlon Brando"
    },
    {
        "query": "Marlon Brando starred as Vito Corleone in ___ which helped him win his second Academy Award.",
        "answer": "The Godfather",
        "level": "1",
        "type": "cloze",
        "subject": "Marlon Brando"
    },
    {
        "query": "After a series of box-office failures, Marlon Brando won an Academy Award for his role in ___.",
        "answer": "The Godfather",
        "level": "1",
        "type": "cloze",
        "subject": "Marlon Brando"
    }
]