[
    {
        "query": "Which of the following films did Bill Paxton star in: Aliens, Pulp Fiction, Forrest Gump?",
        "answer": "Aliens",
        "level": "3",
        "type": "multiple choice",
        "subject": "Bill Paxton"
    },
    {
        "query": "Who portrayed Randall McCoy in the History channel miniseries Hatfields & McCoys?",
        "answer": "Bill Paxton",
        "level": "3",
        "type": "reverse query",
        "subject": "Bill Paxton"
    },
    {
        "query": "Assuming you are a historian specializing in American cinema, could you tell me which HBO drama series earned Bill Paxton three Golden Globe nominations?",
        "answer": "Big Love",
        "level": "3",
        "type": "role play",
        "subject": "Bill Paxton"
    },
    {
        "query": "Please answer in English. Cu\u00e1l pel\u00edcula de 1996 protagonizada por William Paxton trata sobre cazadores de tornados?",
        "answer": "Twister",
        "level": "3",
        "type": "cross lingual (Spanish)",
        "subject": "Bill Paxton"
    },
    {
        "query": "I remember fondly the HBO drama series Big Love, which was quite an engaging watch. Can you tell me, who was the lead actor in this series?",
        "answer": "Bill Paxton",
        "level": "3",
        "type": "prefix injection",
        "subject": "Bill Paxton"
    },
    {
        "query": "William Paxton (May 17, 1955 \u2013 February 25, 2017) was an American actor and filmmaker. He starred in which 1997 blockbuster film?",
        "answer": "Titanic",
        "level": "3",
        "type": "context hint",
        "subject": "Bill Paxton"
    },
    {
        "query": "Which of the following movies featured Bill Paxton: Aliens, Gladiator, The Terminator?",
        "answer": "Aliens",
        "level": "3",
        "type": "multiple choice",
        "subject": "Bill Paxton"
    },
    {
        "query": "Question: What movie did Bill Paxton star in that also featured an extreme weather disaster? Answer: Twister Question: For which series did he receive multiple Golden Globe nominations?",
        "answer": "Big Love",
        "level": "3",
        "type": "incontext learning",
        "subject": "Bill Paxton"
    },
    {
        "query": "I absolutely love the intensity of storm-chasing movies. Do you know which movie Bill Paxton starred in that centered around severe weather?",
        "answer": "Twister",
        "level": "3",
        "type": "prefix injection",
        "subject": "Bill Paxton"
    },
    {
        "query": "William Paxton (May 17, 1955 \u2013 February 25, 2017) was an American actor and filmmaker, known for his dynamic roles. Can you name the HBO drama series he starred in from 2006 to 2011?",
        "answer": "Big Love",
        "level": "3",
        "type": "context hint",
        "subject": "Bill Paxton"
    },
    {
        "query": "Who portrayed Randall McCoy in the History channel miniseries Hatfields & McCoys?",
        "answer": "Bill Paxton",
        "level": "3",
        "type": "reverse query",
        "subject": "Bill Paxton"
    },
    {
        "query": "Pretending you're a movie critic, which film featuring Bill Paxton involves a catastrophic ship sinking?",
        "answer": "Titanic",
        "level": "3",
        "type": "role play",
        "subject": "Bill Paxton"
    },
    {
        "query": "Please answer in English. \u00bfEn qu\u00e9 pel\u00edcula de 1997 protagonizada por Bill Paxton se narra la historia de un naufragio hist\u00f3rico?",
        "answer": "Titanic",
        "level": "3",
        "type": "cross lingual (Spanish)",
        "subject": "Bill Paxton"
    },
    {
        "query": "Question: In which film did Bill Paxton play a storm chaser? Answer: Twister Question: And in which film did he co-star with Tom Hanks depicting an ill-fated space mission?",
        "answer": "Apollo 13",
        "level": "3",
        "type": "incontext learning",
        "subject": "Bill Paxton"
    },
    {
        "query": "Which of the following roles did John Lane Paxton play: a businessman, an actor, a filmmaker?",
        "answer": "an actor",
        "level": "3",
        "type": "multiple choice",
        "subject": "Bill Paxton"
    },
    {
        "query": "Please answer in English. En qu\u00e9 pel\u00edcula de magnicidio producida por Bill Paxton se relata el asesinato en Dallas?",
        "answer": "Parkland",
        "level": "3",
        "type": "cross lingual (Spanish)",
        "subject": "Bill Paxton"
    },
    {
        "query": "Bill Paxton (born May 17, 1955) pursued acting after moving to Los Angeles. In which city was Bill Paxton born?",
        "answer": "Fort Worth, Texas",
        "level": "3",
        "type": "context hint",
        "subject": "Bill Paxton"
    },
    {
        "query": "Which of the following actors had a parent who also acted during his career: Leonardo DiCaprio, Tom Hanks, Bill Paxton?",
        "answer": "Bill Paxton",
        "level": "3",
        "type": "multiple choice",
        "subject": "Bill Paxton"
    },
    {
        "query": "Question: Where was Bill Paxton born and raised?\nAnswer: Fort Worth, Texas\nQuestion: Which film produced by Bill Paxton details the President Kennedy assassination?",
        "answer": "Parkland",
        "level": "3",
        "type": "incontext learning",
        "subject": "Bill Paxton"
    },
    {
        "query": "Bill Paxton was born in Fort Worth, Texas, on May 17, 1955. What high school did he graduate from?",
        "answer": "Arlington Heights High School",
        "level": "3",
        "type": "context hint",
        "subject": "Bill Paxton"
    },
    {
        "query": "Please respond in English. \u00bfEn qu\u00e9 filme, relacionado con el asesinato de un presidente, particip\u00f3 Bill Paxton como coproductor?",
        "answer": "Parkland",
        "level": "3",
        "type": "cross lingual (Spanish)",
        "subject": "Bill Paxton"
    },
    {
        "query": "Which of these roles did Bill Paxton portray in 'Weird Science': school principal, Chet Donnelly, science teacher?",
        "answer": "Chet Donnelly",
        "level": "3",
        "type": "multiple choice",
        "subject": "Bill Paxton"
    },
    {
        "query": "Question: Who directed the music video for the song 'Fish Heads' by Barnes & Barnes? Answer: Bill Paxton Question: What science fiction film did this director act in during 1986?",
        "answer": "Aliens",
        "level": "3",
        "type": "incontext learning",
        "subject": "Bill Paxton"
    },
    {
        "query": "In which role did Bill Paxton appear in the 1982 Pat Benatar music video among the following: a Nazi radio officer, a British spy, a French resistance fighter?",
        "answer": "a Nazi radio officer",
        "level": "3",
        "type": "multiple choice",
        "subject": "Bill Paxton"
    },
    {
        "query": "Whose performance as Private William Hudson in Aliens has been critically acclaimed?",
        "answer": "Bill Paxton",
        "level": "3",
        "type": "reverse query",
        "subject": "Bill Paxton"
    },
    {
        "query": "Pretending to be a film critic, can you list a film from 1986 where Bill Paxton played a notable military character?",
        "answer": "Aliens",
        "level": "3",
        "type": "role play",
        "subject": "Bill Paxton"
    },
    {
        "query": "I'm a big fan of the film Aliens. Could you tell me who played Private William Hudson in that movie?",
        "answer": "Bill Paxton",
        "level": "3",
        "type": "prefix injection",
        "subject": "Bill Paxton"
    },
    {
        "query": "What type of character did Bill Paxton portray in the music video for Pat Benatar's 'Shadows of the Night' among the following: a Nazi radio officer, a British pilot, a Soviet soldier?",
        "answer": "a Nazi radio officer",
        "level": "3",
        "type": "multiple choice",
        "subject": "Bill Paxton"
    },
    {
        "query": "Please answer in English. \u00bfEn qu\u00e9 video musical dirigido por \u00e9l mismo, Bill Paxton us\u00f3 una canci\u00f3n de Barnes & Barnes?",
        "answer": "Fish Heads",
        "level": "3",
        "type": "cross lingual (Spanish)",
        "subject": "Bill Paxton"
    }
]