[
    {
        "question": "Cassandra was the pseudonym of which writer in the Daily Mirror?",
        "answers": [
            "William Neil Connor",
            "William Connor"
        ],
        "subject": "Daniel Day-Lewis"
    },
    {
        "question": "What is written on the cake that Alice finds once she's entered the rabbit hole?",
        "answers": [
            "Eat me",
            "Eat Me!",
            "Eat Me",
            "Eat Me (disambiguation)"
        ],
        "subject": "Daniel Day-Lewis"
    },
    {
        "question": "Who was the Muse of Comedy?",
        "answers": [
            "Thalia (album)",
            "\u0398\u03ac\u03bb\u03b5\u03b9\u03b1",
            "Thalia (Greek mythology)",
            "THALIA",
            "Thalia",
            "Thalia (disambiguation)"
        ],
        "subject": "Daniel Day-Lewis"
    },
    {
        "question": "In years and days, how old was Luigina Giavotti when she won a silver medal in gymnastics in 1928, and is still the youngest medal winner today?",
        "answers": [
            "11 years and 302 days"
        ],
        "subject": "Daniel Day-Lewis"
    },
    {
        "question": "Which 1800 battle saw Napoleon's forces victorious over the Austrians near Alessandria in Piedmont?",
        "answers": [
            "Marengo (disambiguation)",
            "Marengo",
            "MARENGO"
        ],
        "subject": "Daniel Day-Lewis"
    },
    {
        "question": "In which country was the first 24 hour race for motor cars held on a closed course, in 1907?",
        "answers": [
            "Englnad",
            "The land of the Angles",
            "Sasainn",
            "England, U.K.",
            "Engla land",
            "England's",
            "Starks Field School",
            "Englaland",
            "English Nation",
            "Ingland",
            "Engelond",
            "Englistan",
            "Languages of England",
            "England, UK",
            "Name of England",
            "Auld enemy",
            "Sasana",
            "England, United Kingdom",
            "\u00c6ngland",
            "Lloegr",
            "Land of the Angles",
            "Engla rice",
            "Aengland",
            "UK, (England)",
            "\u00c6nglaland",
            "England",
            "Life in England",
            "Aenglaland",
            "ENGLAND",
            "Anglica",
            "Etymology of England",
            "Pow Sows",
            "\u00c6ngla land"
        ],
        "subject": "Daniel Day-Lewis"
    },
    {
        "question": "What colour is the number 10 on the door of 10 Downing Street? White, Yellow or Brown?",
        "answers": [
            "White (Colour)",
            "Rgb(255, 255, 255)",
            "White",
            "Whitishness",
            "Whiter",
            "(255, 255, 255)",
            "Whitishly",
            "White (political adjective)",
            "White-",
            "White-Finn",
            "Whitest",
            "FFFFFF",
            "Color/white",
            "Man on a white horse"
        ],
        "subject": "Daniel Day-Lewis"
    },
    {
        "question": "In which novel does Flora Poste move to live with her relatives, the Starkadders, in Sussex?",
        "answers": [
            "I saw something nasty in the woodshed",
            "Flora Poste",
            "Cold Comfort Farm"
        ],
        "subject": "Daniel Day-Lewis"
    },
    {
        "question": "Which month of the year comes third alphabetically?",
        "answers": [
            "December",
            "\u32cb",
            "Xber",
            "Dec.",
            "Decembre"
        ],
        "subject": "Daniel Day-Lewis"
    },
    {
        "question": "The music of which band finally became available for download from iTunes in November 2010?",
        "answers": [
            "Fab 4",
            "The Silver Beetles",
            "The Nerk Twins",
            "Silver Beats",
            "Nerk Twins",
            "The Beatles (band)",
            "The Beatals",
            "The BEATLES",
            "John, Paul, George, and Ringo",
            "Fab Four",
            "The Beatle",
            "John paul george ringo",
            "Die Beatles",
            "Silver Beatles",
            "Beatles",
            "Silver Beetles",
            "Beatles music",
            "Johnny and the Moondogs",
            "The Silver Beats",
            "Fab four",
            "John, Paul, George and Ringo",
            "TheBeatles",
            "Fab4",
            "Beatles (The)",
            "Johnny and The Moondogs",
            "Johnny and the moondogs",
            "The fab four",
            "History of The Beatles",
            "The Silver Beatles",
            "The Fab Four",
            "Pop Go The Beatles",
            "History of the Beatles",
            "Beatle",
            "The Beetles",
            "Outfake",
            "Johnny And The Moondogs",
            "The Beatles",
            "The beatles",
            "Beatals",
            "The Bealtes",
            "The Fabulous Silver Beatles",
            "Beatles, The",
            "Outfakes",
            "The Beetals",
            "Johnny & The Moondogs",
            "Beatles, the"
        ],
        "subject": "Daniel Day-Lewis"
    },
    {
        "question": "What is the symbol for a 30th wedding anniversary?",
        "answers": [
            "Pearl farm",
            "Pearl farmer",
            "Oyster pearl",
            "Pearl",
            "Pearls",
            "Coloured pearls",
            "Pearl farming",
            "Natural pearl"
        ],
        "subject": "Daniel Day-Lewis"
    },
    {
        "question": "Jean Bastien-Thiry's assassination attempt on Charles de Gaulle in 1962 is the main inspiration behind what 1971 all-time great thriller?",
        "answers": [
            "The Day of the Jackal by Frederick Forsyth"
        ],
        "subject": "Daniel Day-Lewis"
    },
    {
        "question": "Private Eye refers to which member of the Royal Family as Keith?",
        "answers": [
            "DUKE OF EDINBURGH / PRINCE PHILIP"
        ],
        "subject": "Daniel Day-Lewis"
    },
    {
        "question": "Which city is the headquarters of the Mormon church",
        "answers": [
            "Salt Lake, Utah",
            "Kilby Court",
            "Salt Lake City, Ut",
            "Salt Lake city",
            "Salt Lake City, UT, USA",
            "Salt Lake City, Utah",
            "Salt Lake City, USA",
            "SL, UT",
            "UN/LOCODE:USSLC",
            "Salt Lake City, UT",
            "Salt lake city",
            "Grid plan (Salt Lake City)",
            "Utah state capital",
            "Capital of Utah",
            "Salt Lake City , Utah",
            "Salt Lake Cit",
            "Salt Lake City, Utah, USA",
            "Salt Lake, UT",
            "Saltlake City",
            "J. E. Cosgriff Memorial Catholic School",
            "J.E. Cosgriff Memorial Catholic School",
            "Salt Lake City",
            "Great Salt Lake City",
            "Salt Lake City (UT)"
        ],
        "subject": "Daniel Day-Lewis"
    },
    {
        "question": "Nicknamed 'Robo Cop' when a policeman, Ray Mallon is the directly elected Mayor of which town?",
        "answers": [
            "Port Darlington",
            "Middlesburgh",
            "Middlesborough, England",
            "Middlesbrough, Cleveland",
            "Middlesbrough, Teesside",
            "County Borough of Middlesbrough",
            "Areas with in Middlesbrough",
            "Middlesbrough, Tees Valley",
            "Middlesbrough (borough)",
            "Middlesbrough, North Yorkshire",
            "Middlesbrough",
            "Middlesbrough, England",
            "Middlesbrough UA",
            "Ironopolis",
            "The weather in Middlesbrough",
            "Middlesbrough Dock",
            "Areas within Middlesbrough",
            "MIDDLESBROUGH"
        ],
        "subject": "Daniel Day-Lewis"
    },
    {
        "question": "Anne of Bohemia was the wife of which English king?",
        "answers": [
            "Richard ii",
            "Richard II, King of the English",
            "Richard, Duke of Cornwall",
            "Richard II (England)",
            "Richard II, King of England",
            "Richard II",
            "King Richard II of England",
            "RICHARD II",
            "King Richard II",
            "Richard II of england",
            "Richard II of England"
        ],
        "subject": "Daniel Day-Lewis"
    },
    {
        "question": "Han of Iceland, Oedipus in Athens & The Ballet of Unhatched Chicks are all works by which composer?",
        "answers": [
            "Modest Petrovich Mussorgsky",
            "Modest musorgsky",
            "Modest Petrovich Moussorgsky",
            "Modeste Petrovich Moussorgsky",
            "\u041c\u043e\u0434\u0435\u0441\u0442 \u041f\u0435\u0442\u0440\u043e\u0432\u0438\u0447 \u041c\u0443\u0441\u043e\u0440\u0433\u0441\u043a\u0438\u0439",
            "Modest mussourgsky",
            "Modest Musorgsky",
            "(Modest) Mussorgsky",
            "Musorgsky",
            "Modest Musorgski",
            "Modeste Mussorgski",
            "Mussorgski",
            "Modest Mussorgski",
            "Modest Moussorgsky",
            "Mussorgskian",
            "Modeste Mussorgsky",
            "Mussorgsky",
            "Modest Mussorgsky",
            "Moussorgsky",
            "Modeste Mussourgsky",
            "Modest Moussorgski",
            "Modest Petrovich Musorgsky",
            "\u041c\u043e\u0434\u0435\u0301\u0441\u0442 \u041f\u0435\u0442\u0440\u043e\u0301\u0432\u0438\u0447 \u041c\u0443\u0301\u0441\u043e\u0440\u0433\u0441\u043a\u0438\u0439",
            "Modest Petrowitsch Mussorgsky",
            "Modest Musorgskiy",
            "Modeste Moussorgsky"
        ],
        "subject": "Daniel Day-Lewis"
    },
    {
        "question": "What fruity name do the French call a bowler hat?",
        "answers": [
            "Casaba",
            "Melons",
            "Tuscan melon",
            "\ud83c\udf48",
            "List of melons",
            "Kwaci",
            "Canadew",
            "Melon",
            "Tuscan canteloupe"
        ],
        "subject": "Daniel Day-Lewis"
    },
    {
        "question": "Who was Richard Nixon's running mate in the 1960 US presidential election?",
        "answers": [
            "Lodge, Henry Cabot",
            "Slim Lodge",
            "Henry Cabot Lodge, Sr.",
            "Henry Cabot Lodge Sr.",
            "Henry C. Lodge",
            "Henry Cabot Lodge (1850-1924)",
            "Henry Cabot Lodge",
            "Lodge, Henry Cabot (1850-1924)"
        ],
        "subject": "Daniel Day-Lewis"
    },
    {
        "question": "In terms of tonnage of cargo handled, which is the world's largest port?",
        "answers": [
            "Rotterdam South",
            "Rotterdam, South Holland",
            "R'dam",
            "Historisch Museum Rotterdam",
            "UN/LOCODE:NLRTM",
            "Rotterdam, Holland",
            "Roterdam",
            "Rotterdam, Netherlands",
            "Rotterdam",
            "Rotterdam, Zuid Holland"
        ],
        "subject": "Daniel Day-Lewis"
    },
    {
        "question": "What now illegal crop did George Washington grow on his estate?",
        "answers": [
            "Natural fibre hemp",
            "Hempmilk",
            "Ditchweed",
            "Industrial hemp",
            "Hempseed",
            "Hempnut",
            "Hemp paper",
            "Shelled Hemp Seeds",
            "Commercial hemp",
            "Hemp (cannabis oglalas)",
            "Industrial cannabis",
            "Hemp nut",
            "Hemp seed",
            "Hempen",
            "Hemp",
            "Hemp rope",
            "Industrial Hemp"
        ],
        "subject": "Daniel Day-Lewis"
    },
    {
        "question": "Director of Home Alone and the first two Harry Potter films and a 15th/16th century Genoese explorer.",
        "answers": [
            "Christoffa Corombo",
            "Christopher columbus",
            "Col\u00f3n, Crist\u00f3bal-- Explorer",
            "Crostoforo Colombo",
            "Chistopher Colombus",
            "Christopher Colombus",
            "Cristoforo Colubmo",
            "Christophorus Columbus",
            "Columbus Quincentennial",
            "Crist\u00f3bal Col\u00f3n",
            "Columbus's",
            "Christoper Columbus",
            "Crist\u00f3v\u00e3o Colombo",
            "Christovao Columbo",
            "Cristoforo Colombo",
            "Cristopher Colombus",
            "Christopher columb",
            "CHRISTOPHER COLUMBUS",
            "Christopher colub",
            "Christopher Columbus 1st Voyage",
            "Colon, Cristobal-- Explorer",
            "Perceptions of Columbus",
            "Cristobol Colon",
            "Topher columbus",
            "Cristovao Colombo",
            "Christofo Columbo",
            "Christopher Columbus",
            "Christopher coloumbus",
            "Christobal Colon",
            "Admiral of the Ocean Sea",
            "Cristopher Columbus",
            "Cristoforo Columbo"
        ],
        "subject": "Daniel Day-Lewis"
    },
    {
        "question": "Name either British coin that ceased to be legal tender on August 31st. 1971?",
        "answers": [
            "THREEPENCE or ONE PENNY (3d. or 1d.)"
        ],
        "subject": "Daniel Day-Lewis"
    },
    {
        "question": "The Bell Rock Lighthouse, said to be the oldest surviving offshore lighthouse in the world, lies off the coast of which European country?",
        "answers": [
            "The Scottish Nation",
            "Scotlander",
            "Scotland",
            "Northern Great Britain",
            "Scot Land",
            "Scottland",
            "Scotlanders",
            "Scotland, UK",
            "Scotland's",
            "Scottish nation",
            "North Great Britain",
            "Autonomous Province of Scotland",
            "Scottish Nation",
            "Communications in Scotland",
            "Maps of scotland",
            "North of Great Britain",
            "Scotia minor",
            "Auld Country",
            "Scotchland",
            "H-Alba",
            "SCOTLAND",
            "East coast of Scotland"
        ],
        "subject": "Daniel Day-Lewis"
    },
    {
        "question": "What was the name of the Liverpool nightclub where the Beatles regularly played?",
        "answers": [
            "Cavern club",
            "Cavern Club",
            "The Cavern",
            "Alan Sytner",
            "The Cavern Club"
        ],
        "subject": "Daniel Day-Lewis"
    },
    {
        "question": "In 1968, what telephone number was established as the national emergency number for the United States?",
        "answers": [
            "nine hundred and eleven",
            "911"
        ],
        "subject": "Daniel Day-Lewis"
    },
    {
        "question": "Which American wit said, 'This is not a novel to be tossed aside lightly. It should be thrown with great force'?",
        "answers": [
            "Constant Reader",
            "Algonquin wit",
            "Sunset Gun",
            "Dot parker",
            "Dorothy Parker",
            "Dorothy Rothschild Parker",
            "Dottie Parker",
            "Dorothy Rothschild"
        ],
        "subject": "Daniel Day-Lewis"
    },
    {
        "question": "Caroline of Brunswick was the queen of which British king?",
        "answers": [
            "George, Prince Regent",
            "King George IV of the United Kingdom",
            "GEORGE IV",
            "George the Fourth",
            "George IV of Great Britain",
            "George IV of the UK",
            "King George IV",
            "George IV of Great Britain and Ireland",
            "George IV of the United Kingdom",
            "George IV",
            "Regency Bill",
            "George IV of England",
            "George IV of Scotland",
            "George IV Hanover",
            "George IV of Hanover",
            "George iv",
            "George iv of the united kingdom",
            "George IV of Britain",
            "George IV (Hanover)"
        ],
        "subject": "Daniel Day-Lewis"
    },
    {
        "question": "Which company produces the 'Fireblade' motorcycle?",
        "answers": [
            "Honda Technologies",
            "HONDA",
            "Honda atv",
            "Honda Motor Company, Limited",
            "Honda Clio",
            "Honda Soltec",
            "Honda (automobile)",
            "Honda Outboard",
            "Honda Motor Co.",
            "Honda Motor Company Limited",
            "Honda Corporation",
            "Honda Verno",
            "Honda",
            "Honda Group",
            "Honda motorcycle",
            "\u672c\u7530",
            "Soltec",
            "Honda Motor Co., Ltd.",
            "Hero honda passion plus",
            "Cbr 150",
            "Honda Motor Company Inc.",
            "Honda motorcycles",
            "Honda Motor Company",
            "Honda Motor Co. Ltd.",
            "Honda 300ex",
            "Honda CL145",
            "Honda Motorcycles",
            "Honda Primo",
            "Honda Motor Manufacturing",
            "Honda Werther",
            "Honda Motor"
        ],
        "subject": "Daniel Day-Lewis"
    },
    {
        "question": "Which country since the late 1900s has governed/overseen the increasing independence of the New Caledonia archipelago, east of Australia?",
        "answers": [
            "La Republique francaise",
            "Franciaorsz\u00e1g",
            "La Republique fran\u00e7aise",
            "Belle France",
            "FRANCE",
            "Republique fran\u00e7aise",
            "France",
            "Ranska",
            "Franciaorszag",
            "French Republic",
            "R\u00e9publique francaise",
            "R\u00e9publique fran\u00e7aise",
            "ISO 3166-1:FR",
            "Frankreich",
            "France (country)",
            "Etymology of France",
            "FrancE",
            "La R\u00e9publique fran\u00e7aise",
            "People of France",
            "Republic of France",
            "Fracne",
            "Le France",
            "The French Republic",
            "Republique francaise",
            "The Republic of France",
            "La R\u00e9publique francaise",
            "La France",
            "Rain in France",
            "Republic of france",
            "FRance",
            "Frakkland",
            "Climate of France",
            "Franse"
        ],
        "subject": "Daniel Day-Lewis"
    },
    {
        "question": "In which city is Green Square, the scene of protests in 2011?",
        "answers": [
            "The Mermaid of the Mediterranean",
            "Trablus Garb",
            "Tripoli, LY",
            "Western Tripoli",
            "Tarablusi Garb",
            "Tar\u0101bulus",
            "\u0637\u0631\u0627\u0628\u0644\u0633 \u0627\u0644\u063a\u0631\u0628",
            "UN/LOCODE:LYTIP",
            "Tripoli",
            "Tripoli (city, Libya)",
            "Capital of Libya",
            "Tripoli, Libya",
            "African Tripoli",
            "\u0162ar\u0101bulus",
            "Tripali",
            "\u0162ar\u0101bulus District",
            "\u0637\u0631\u0627\u0628\u0644\u0633"
        ],
        "subject": "Daniel Day-Lewis"
    },
    {
        "question": "What is either a city in Germany or a type of fragrance?",
        "answers": [
            "UN/LOCODE:DECGN",
            "Cologne, Germany",
            "City of Cologne",
            "Colonia Agrippinae",
            "Koln",
            "Cologne",
            "K\u00f6lle",
            "DECGN",
            "Koeln",
            "C\u00f6ln am Rhein",
            "K\u00f6ln (region)",
            "K\u00f6ln, Germany",
            "K\u00f6ln",
            "Cologne (Germany)",
            "C\u00f6ln",
            "Cologner",
            "Koeln, Germany",
            "Oppidum Ubiorum",
            "Coln",
            "Koln, Germany",
            "Keulen",
            "Culture of Cologne"
        ],
        "subject": "Daniel Day-Lewis"
    },
    {
        "question": "How many times was Boris Becker runner-up in the Men's Singles at Wimbledon?",
        "answers": [
            "four",
            "4"
        ],
        "subject": "Daniel Day-Lewis"
    },
    {
        "question": "Whose last opera was 'The Golden Cockerel'?",
        "answers": [
            "Nikolai Rimsky Korsakov",
            "Rimsky Korsakoff",
            "NIKOLAI RIMSKY- KORSAKOV",
            "Nikolay Rimsky-Korsakov",
            "Rimsky-Korsakov, Nikolay Andreyevich",
            "Nikolai Andreyevich Rimski-Korsakov",
            "Rimsky-korsakov",
            "Rimskij-Korsakov",
            "Nikolay Andreyevich Rimsky-Korsakoff",
            "Rimsky-Korsakof",
            "Nikolay Rimsky-Korsakoff",
            "Nikolai Andreyevich Rimsky-Korsakoff",
            "Nikolai Andrejewitsch Rimsky-Korsakow",
            "Nikolaj Andreevi\u010d Rimskij-Korsakov",
            "Rimsky korsakov",
            "Rimsy-korsakov",
            "Nikolaj Rimskij-Korsakov",
            "Rimsky-Korsakov",
            "Nikolai Rimsky-Korsakoff",
            "Nicolas Andreievich Rimsky-Korsakov",
            "Nicolai Andreyevich Rimsky-Korsakov",
            "Nikolaj Rimsky-Korsakov",
            "Nikolaj Andreevic Rimskij-Korsakov",
            "Nikolay Andreyevich Rimsky-Korsakov",
            "\u041d\u0438\u043a\u043e\u043b\u0430\u0439 \u0420\u0438\u043c\u0441\u043a\u0438\u0439-\u041a\u043e\u0440\u0441\u0430\u043a\u043e\u0432",
            "Nikolai Rimsky-Korsakov",
            "Nikolai Andreievich Rimsky-Korsakov",
            "Nikolai Andreyevich Rimsky-Korsakov",
            "Nicolas Rimsky-Korsakov",
            "Nicolai Rimsky-Korsakov",
            "Rimsky-Korsakoff",
            "Rimsky-Korsakov, Nicolai Andreyevich",
            "Nikolai Andreevich Rimski-Korsakov",
            "Nikolai Rimski-Korsakov",
            "Nikolay Rimsky Korsakov",
            "Nikolai Rimsky Korsakoff"
        ],
        "subject": "Daniel Day-Lewis"
    },
    {
        "question": "On obtaining city status, St Asaph became the second city in the UK; which is the smallest?",
        "answers": [
            "Smallest?"
        ],
        "subject": "Daniel Day-Lewis"
    },
    {
        "question": "Tu is the clothing brand of supermarket chain?",
        "answers": [
            "Sainsburys.com",
            "Sansburys",
            "Sainsbury (J)",
            "Beaumonts",
            "Sainsbury (J) plc",
            "SL Shaw Ltd",
            "By Sainsbury's",
            "Sainsbury's Energy",
            "Sainsburys",
            "Sainsbury's Basics",
            "Sainsbury's Calais",
            "J Sainsbury PLC",
            "Sainsbury\u2019s",
            "Sainsbury's Supermarkets",
            "J. Sainsbury plc",
            "J Sainsbury",
            "JB Beaumont",
            "J Sainsbury plc",
            "SL Shaw",
            "J Sainsbury's",
            "Sainsbury's Entertainment",
            "J. Sainsbury",
            "Sainsbury's"
        ],
        "subject": "Daniel Day-Lewis"
    },
    {
        "question": "Which Liverpool player scored two goals in both the semi-final and final of the FA Cup in 1986?",
        "answers": [
            "IAN RUSH",
            "Ian Rush"
        ],
        "subject": "Daniel Day-Lewis"
    },
    {
        "question": "What breed of dog is the \u2018Monopoly\u2019 playing piece, or token?",
        "answers": [
            "Scottie dog",
            "Aberdeen Terrier",
            "Scottish terrier",
            "Scottish Highlands White Terrier",
            "Scotch terrier",
            "Scottie",
            "SCOTTISH TERRIER",
            "Scottish Terrier",
            "Scotty dog",
            "Scotch Terrier"
        ],
        "subject": "Daniel Day-Lewis"
    },
    {
        "question": "Which British comedy-drama series (1979 to 1994) starred George Cole as Arthur Daley, an unscrupulous importer-exporter, wholesaler, and used-car salesman and Dennis Waterman as Terry McCann, his bodyguard?",
        "answers": [
            "Minder"
        ],
        "subject": "Daniel Day-Lewis"
    },
    {
        "question": "In the Children?s TV series Peppa Pig who is Peppa's best friend?",
        "answers": [
            "Suzy (disambiguation)",
            "Suzy"
        ],
        "subject": "Daniel Day-Lewis"
    },
    {
        "question": "Which is the smallest bird of the crow family?",
        "answers": [
            "Graculus",
            "Eurasian Jackdaw",
            "European Jackdaw",
            "Corvus monedula",
            "Monedula",
            "Eurasian jackdaw",
            "Coloeus monedula",
            "Western jackdaw",
            "Jackdaw",
            "Western Jackdaw"
        ],
        "subject": "Daniel Day-Lewis"
    },
    {
        "question": "Who, in 1936, painted a portrait of Mae West in which her face is also a furnished room?",
        "answers": [
            "Salvador Felipe Jacinto DalA",
            "Daliesque",
            "Salvador Felip Jacint Dali Domenech",
            "Dal\u00edesque",
            "Salvador Felip Jacint Dal\u00ed Dom\u00e8nech",
            "Salvador Felipe Jacinto Dali",
            "Meanings of Paintings by Salvador Dali",
            "Dal\u00ed",
            "Nuclear cross",
            "Salvador Dali i Domenech",
            "Dali Lithograph",
            "Salvador Domingo Felipe Jacinto Dal\u00ed i Domenech",
            "Salvador Domingo Felipe Jacinto Dal\u00ed i Dom\u00e8nech, 1st Marquis of P\u00fabol",
            "Dali salvador",
            "Salvador Domingo Felipe Jacinto Dali i Domenech",
            "Salvador dhali",
            "Salvadore Dali",
            "Salvador Dal\u00ec",
            "Salvador Dal\u00ed",
            "Salvador Domingo Felipe Jacinto Dali i Dom\u00e8nech",
            "Salvador Dali",
            "Salvador Dal\u00ed i Dom\u00e8nech",
            "Salvador Domenec Felip Jacint Dali Domenech",
            "Marques de Pubol",
            "(Salvador) Dali",
            "Salvador Domingo Felipe Jacinto Dal\u00ed i Dom\u00e8nech",
            "Salvador Domenec Felip Jacint Dal\u00ed Domenech",
            "Salvador dal\u00ec",
            "Salvador dali",
            "Salvador Felipe Jacinto Dali i Domenech",
            "The Meanings of the Paintings of Salvador Dali",
            "Avida Dollars",
            "Salvidor Dali"
        ],
        "subject": "Daniel Day-Lewis"
    },
    {
        "question": "The English towns of Abingdon, Wallingford and Marlow lie on which river?",
        "answers": [
            "Theems",
            "Thames River",
            "The Thames",
            "River Thames",
            "Tamisa",
            "Themsen",
            "Themse",
            "Old Father Thames",
            "Thames river",
            "Tamiza",
            "Temze",
            "History of Thames Water",
            "Temza",
            "The Thames River",
            "The River Thames",
            "Tamesa",
            "River Temz",
            "Thames Crossing",
            "Tamigi",
            "Temz River",
            "River Tems",
            "The Thames (river)",
            "Tems River",
            "Thames Basin",
            "River thames",
            "Isis River (England)",
            "Thames (river)",
            "Thames",
            "Thames River (England)"
        ],
        "subject": "Daniel Day-Lewis"
    },
    {
        "question": "Which of Queen Elizabeth's children is the lowest in succession to (i.e. furthest away from) the throne?",
        "answers": [
            "Anne",
            "Ann (name)"
        ],
        "subject": "Daniel Day-Lewis"
    },
    {
        "question": "Who has recently overtaken Brian O'Driscoll to become Ireland's most capped player?",
        "answers": [
            "RONAN O'GARA",
            "O'Gara",
            "Ronan O'Gara",
            "Ronan O\u2019Gara"
        ],
        "subject": "Daniel Day-Lewis"
    },
    {
        "question": "The book Eunoia, by Christian Bok, suggests in its title, and features exclusively what, in turn, in its first five chapters?",
        "answers": [
            "The vowels a, e, i, o, u."
        ],
        "subject": "Daniel Day-Lewis"
    },
    {
        "question": "In Camberwick Green on Children's TV who was the commander of Pippin Fort?",
        "answers": [
            "CAPTAIN SNORT"
        ],
        "subject": "Daniel Day-Lewis"
    },
    {
        "question": "What is the American version of Strictly Come Dancing called?",
        "answers": [
            "Strictly Keep Dancing",
            "Dancing With The Stars",
            "Dwts",
            "Strictly keep dancing",
            "DWTS",
            "Dansez Pentru Tine",
            "Dancing with the Stars",
            "Tantsy so zvezdami",
            "Dancing With the Stars: Keep Dancing",
            "Dancing With the Stars",
            "Dancing with the stars",
            "Dancing with the Stars (Denmark)",
            "Dancing Stars"
        ],
        "subject": "Daniel Day-Lewis"
    },
    {
        "question": "In advertising what is said to refresh the parts others fail to reach?",
        "answers": [
            "Heineken beer",
            "Gerard Adriaan Heineken",
            "Heineken",
            "H. Elion",
            "Heineken Pilsener",
            "HEINEKEN",
            "Heineken Pilsner",
            "Heineken U.S.",
            "Dr. H. Elion"
        ],
        "subject": "Daniel Day-Lewis"
    },
    {
        "question": "Who was the Liberal Prime Minister of Great Britain from 1855 to 1858?",
        "answers": [
            "Palmerston",
            "PALMERSTON",
            "Palmerston (disambiguation)"
        ],
        "subject": "Daniel Day-Lewis"
    },
    {
        "question": "Of what is genuphobia a fear?",
        "answers": [
            "Knees (accept Kneeling)"
        ],
        "subject": "Daniel Day-Lewis"
    },
    {
        "question": "Who was the last non-American (non-Williams) to win the Ladies \\singles at Wimbledon?",
        "answers": [
            "Am\u00e9lie Mauresmo",
            "Mauresmo",
            "Amelie Mauresmo",
            "AMELIE MAURESMO",
            "Amelie mauresmo"
        ],
        "subject": "Daniel Day-Lewis"
    },
    {
        "question": "What is the name for a set of marks stamped on gold and silver articles to attest to the genuineness of the metal and the year of testing?",
        "answers": [
            "Hall-mark",
            "Hallmark",
            "Hallmarks",
            "Hall-Mark",
            "Hall mark",
            "Hall Mark"
        ],
        "subject": "Daniel Day-Lewis"
    },
    {
        "question": "The internal angles of an octagon add up to how many degrees?",
        "answers": [
            "1,080",
            "one thousand and eighty",
            "1080"
        ],
        "subject": "Daniel Day-Lewis"
    },
    {
        "question": "\"Who wrote the music for the musical \"\"A Chorus Line\"\"?\"",
        "answers": [
            "Marvin Frederick Hamlisch",
            "Marvin Hamlish",
            "Marvin Hamlisch"
        ],
        "subject": "Daniel Day-Lewis"
    },
    {
        "question": "Which half of a comedy duo was born in Lancashire in 1895?",
        "answers": [
            "Arthur Stanley Jefferson",
            "Stan Laurel",
            "Stanley Laurel",
            "Arthur Jefferson"
        ],
        "subject": "Daniel Day-Lewis"
    },
    {
        "question": "What kind of animal are Chip and Dale?",
        "answers": [
            "Chipmonk",
            "Chip monk",
            "Chipmunk",
            "Microbear",
            "Tamias",
            "Chipmunks",
            "Chip munk",
            "\ud83d\udc3f"
        ],
        "subject": "Daniel Day-Lewis"
    },
    {
        "question": "Which American state has the most airports",
        "answers": [
            "Texas (U.S. State)",
            "US-TX",
            "Texos",
            "Texas",
            "Lone Star State",
            "Texas, USA",
            "Religion in Texas",
            "Texas (state)",
            "Lake Ozark, Texas",
            "Christianity in Texas",
            "The State of Texas",
            "Twenty-eighth State",
            "Texas-sized",
            "Texas (State)",
            "28th State",
            "The Lone Star State",
            "Twenty-Eighth State",
            "Texas, United States",
            "Texas (U.S. state)",
            "Texass",
            "State of Texas",
            "Everything is bigger in Texas",
            "28th state"
        ],
        "subject": "Daniel Day-Lewis"
    },
    {
        "question": "Which 1987 US film was based on the 1985 French film \u2018Trois hommes et un couffin\u2019?",
        "answers": [
            "Three Men and a Baby",
            "Three men and a baby",
            "3 Men and a Baby",
            "3 men and a baby",
            "THREE MEN AND A BABY",
            "Peter Mitchell (Three Men and a Baby)",
            "Jack Holden (Three Men and a Baby)"
        ],
        "subject": "Daniel Day-Lewis"
    },
    {
        "question": "Give an example of an 'ordinal number'?",
        "answers": [
            "FIRST, SECOND, THIRD etc"
        ],
        "subject": "Daniel Day-Lewis"
    },
    {
        "question": "A spoof of fraternal organizations such as the Masons, Shriners, Elks Club, or Moose Lodge, of what lodge was Fred Flintstone elected Grand Imperial Poobah?",
        "answers": [
            "Loyal Order of Water Buffalo"
        ],
        "subject": "Daniel Day-Lewis"
    },
    {
        "question": "Which P.G. Wodehouse character has a butler 'Sebastian Beach' and a gardener 'Angus McAllister'?",
        "answers": [
            "Clarence Threepwood, 9th Earl of Emsworth",
            "Clarence Threepwood",
            "9th Earl of Emsworth",
            "Viscount Bosham",
            "Clarence Threepwood, Lord Emsworth",
            "Lord Emsworth",
            "Earl of Emsworth",
            "'LORD EMSWORTH'"
        ],
        "subject": "Daniel Day-Lewis"
    },
    {
        "question": "The technical term abecedarian refers to what form of organization?",
        "answers": [
            "List of letters in the english language",
            "Alphabetical",
            "Abc's",
            "True alphabet",
            "Alphabetic writing system",
            "Alphabetic writing",
            "Alfabet",
            "Alphabet",
            "Alphabetic",
            "Alphebet",
            "Alphabetic writing systems",
            "Aplhabet",
            "Abeceda",
            "Segmentary",
            "Abcs",
            "(alphabet)",
            "Alphabets",
            "Alphabetic language",
            "Alpabet",
            "Letter name",
            "Alphabetic script"
        ],
        "subject": "Daniel Day-Lewis"
    },
    {
        "question": "Which Swiss firm of architects was responsible for the Allianz Arena in Munich and converting B Power Station in London into Tate Modern?",
        "answers": [
            "ERZOG & DE MEURON"
        ],
        "subject": "Daniel Day-Lewis"
    },
    {
        "question": "The world's first publicly subscribed passenger railway, the Stockton and Darlington, opened in England with steam engines when?",
        "answers": [
            "1825",
            "one thousand, eight hundred and twenty-five"
        ],
        "subject": "Daniel Day-Lewis"
    },
    {
        "question": "Which Serbian football club is the only one from that country to win an UEFA completion?",
        "answers": [
            "Red Star Belgrade F.C",
            "Red Star Belgrade F.C.",
            "Crvena Zvezda FK",
            "F.K. Crvena Zvezda",
            "FK Estrella Roja",
            "FK Crvena zvezda",
            "Crevna zvezda",
            "F.C. Red star Belgrade",
            "Red Star Belgrade FC",
            "Crvena zvezda FK",
            "F.K. Crvena zvezda",
            "FK crvena zvezda",
            "FK Crvena Zvezda Beograd",
            "Red Star Belgrade",
            "Red Star Beograd",
            "Fk crvena zvezda",
            "Crvena zvezda Beograd",
            "F.K. Crvena zvezda Beograd",
            "Red star Belgrade FC",
            "Crvena Zvezda F.K.",
            "Red Star of Belgrade",
            "Red star Belgrade",
            "FC Crevna Zvezda",
            "FC Red Star Belgrade",
            "Red star Belgrade F.C.",
            "Crvena Zvezda Beograd",
            "Zvezdina zvezda",
            "F.C Red Star Belgrade",
            "FK Crvena Zvezda",
            "Crvena zvezda F.K.",
            "FK Crvena zvezda Beograd",
            "RED STAR BELGRADE",
            "FC Red star Belgrade",
            "FK Red Star",
            "F.K. Crvena Zvezda Beograd",
            "F.C. Red Star Belgrade"
        ],
        "subject": "Daniel Day-Lewis"
    },
    {
        "question": "In which TV series would you find an Eagle Transporter",
        "answers": [
            "Alpha1999",
            "Space:1999",
            "Space 1999",
            "The Woodgrove Trilogy",
            "Space1999",
            "Alpha 1999",
            "Space: 1999"
        ],
        "subject": "Daniel Day-Lewis"
    },
    {
        "question": "In 'Coronation Street', what was the name of the character played by Roy Hudd?",
        "answers": [
            "List of minor Coronation Street characters (2002)",
            "Angela Nelson",
            "Joshua Peacock",
            "Angela Harris (fictional character)",
            "Angela Nelson/Harris",
            "Angela Harris (Coronation Street)",
            "Tommy Harris (soap character)",
            "Danielle Spencer (Coronation Street)",
            "Katy Nelson/Harris",
            "Katy Harris",
            "List of Coronation Street characters (2002)",
            "Lucy Richards",
            "Craig Harris (Cornonation Street character)",
            "Joe Carter (Coronation Street)",
            "Lillian Spencer",
            "Timothy Spencer (Coronation Street)",
            "'ARCHIE SHUTTLEWORTH'",
            "Archie Shuttleworth",
            "Carol Mills",
            "Stephanie Mills (Coronation Street)",
            "Craig Harris (Coronation Street)",
            "Tommy Harris (Coronation Street)",
            "Patricia Hillman",
            "Killer Katy",
            "John Arnley",
            "Craig Nelson/Harris",
            "Hazel Wilding",
            "Katy Nelson",
            "Goran Milanovic",
            "Patrick Tussell",
            "Craig Harris (Coronation Street character)"
        ],
        "subject": "Daniel Day-Lewis"
    },
    {
        "question": "Who is the female presenter of the Channel 4 quiz show '1001 things you should know'?",
        "answers": [
            "Sandy Toksvig",
            "Sandi Toksvig"
        ],
        "subject": "Daniel Day-Lewis"
    },
    {
        "question": "Where does the Mandarin duck nest?",
        "answers": [
            "(In a hole in a) tree"
        ],
        "subject": "Daniel Day-Lewis"
    },
    {
        "question": "What is the forename of Lewis Hamilton\u2019s father, a prominent member of his entourage?",
        "answers": [
            "Anthony",
            "Anthony Tony",
            "Anthony (disambiguation)"
        ],
        "subject": "Daniel Day-Lewis"
    },
    {
        "question": "What in South America is a pampero?",
        "answers": [
            "WIND (disambiguation)",
            "WIND",
            "A WIND"
        ],
        "subject": "Daniel Day-Lewis"
    },
    {
        "question": "What is the name of the whirlpool in the Hebrides between Scarba and Jura, the third largest in the world?",
        "answers": [
            "Coire Bhreacain",
            "Coire Bhreacan",
            "Gulf of Corryvreckan",
            "Corrievreckan",
            "Corryvreckan",
            "Corry Vreckan",
            "Coirebhreacain",
            "Corryvreckan whirlpool",
            "Corryvrecken"
        ],
        "subject": "Daniel Day-Lewis"
    },
    {
        "question": "Who had a top ten hit in 1988 with Valentine?",
        "answers": [
            "T\u2019pau",
            "T'pau",
            "T'Pau (disambiguation)",
            "T' Pau",
            "T'Pau",
            "T pau",
            "Tpau"
        ],
        "subject": "Daniel Day-Lewis"
    },
    {
        "question": "Who was the Romanian gymnast who scored the first ever perfect ten at the Olympic Games of 1976?",
        "answers": [
            "NADIA COMANECI",
            "Nadia Elena Com\u0103neci",
            "Nadia Com\u0103neci",
            "Comaneci",
            "Nadia Comenici",
            "Nadia Comeneci",
            "Comaneci, Nadia",
            "Nadia Comaneci",
            "Com\u0103neci",
            "Nadia Elena Comaneci",
            "Nadia comeneci"
        ],
        "subject": "Daniel Day-Lewis"
    },
    {
        "question": "What is Australian slang for an outside lavatory?",
        "answers": [
            "Dunny"
        ],
        "subject": "Daniel Day-Lewis"
    },
    {
        "question": "Which much-loved actor won the Best Actor Oscar for The Philadelphia Story?",
        "answers": [
            "James Stewart (actor)",
            "Jimmy Stuart",
            "James stewart (actor)",
            "Jimmy Stewart",
            "James Stewart",
            "Jimmy stewart",
            "Stewart, James"
        ],
        "subject": "Daniel Day-Lewis"
    },
    {
        "question": "What word describes making beautiful with ornaments, or to decorate, etc?",
        "answers": [
            "Embellishment",
            "Embellish",
            "Embellished"
        ],
        "subject": "Daniel Day-Lewis"
    },
    {
        "question": "In which Indian city is Eden Gardens, the second largest test cricket ground in the world?",
        "answers": [
            "Calcuta",
            "Calixestra",
            "Downtown Mumbai",
            "Kalkutta",
            "Culcutta",
            "Colcata",
            "City of Bombay",
            "Kolkata",
            "KOLKATA",
            "Kolkata, WB",
            "Calcutta, WB",
            "City of Mumbai",
            "City of Kolkata",
            "List of Kolkata facts",
            "Kolkata trivia",
            "South Kolkata",
            "Calcutta, India",
            "Kolkota",
            "South Calcutta",
            "Kolkata, India",
            "Calcutta",
            "Demographics of Bombay",
            "City of Calcutta",
            "Calcutta, West Bengal",
            "Kolkata, West Bengal",
            "Calcutta (India)",
            "Kolkatta",
            "Bumbai"
        ],
        "subject": "Daniel Day-Lewis"
    },
    {
        "question": "The South African currency unit, the Rand, is divided into a hundred what?",
        "answers": [
            "Cent (area)",
            "Cent (disambiguation)",
            "Cents",
            "Cent (measure)",
            "Cent",
            "Cent (unit)",
            "CENTS",
            "Cent-"
        ],
        "subject": "Daniel Day-Lewis"
    },
    {
        "question": "For what medical condition would a doctor administer an antipyretic?",
        "answers": [
            "Subfebrile",
            "Low grade fever",
            "Fever",
            "Hyperpyrexia",
            "Pyrexia",
            "Fevers",
            "Febrile",
            "Fever with rash",
            "Pyrogens",
            "FEVER",
            "Fever with Rash",
            "Low-grade fever",
            "Pyrogen (fever)",
            "Pyrogenic",
            "Low-grade pyrexia",
            "Pyretic conditions",
            "Fever phobia"
        ],
        "subject": "Daniel Day-Lewis"
    },
    {
        "question": "In June 2009, General Motors announced that it would sell which of its brands to Tengzhong Heavy Industrial Machinery, based in China?",
        "answers": [
            "Hummer",
            "HUMMER"
        ],
        "subject": "Daniel Day-Lewis"
    },
    {
        "question": "'The Playboy Riots' occurred during and following the opening in 1907 of 'The Playboy Of The Western World' by J.M. Synge, at which Dublin theatre?",
        "answers": [
            "Irish National Theatre Society",
            "ABBEY THEATRE",
            "Irish National Theatre",
            "Peacock Theatre, Dublin",
            "The Abbey Theater",
            "Abbey School of Actors",
            "Abbey School of Acting",
            "National Theatre of Ireland",
            "Abbey Theater",
            "Abbey Theatre, Dublin",
            "Abbey Experimental Theatre Company",
            "Abbey School of Ballet",
            "Abbey Theatre",
            "Abbey Players",
            "The Abbey Theatre"
        ],
        "subject": "Daniel Day-Lewis"
    },
    {
        "question": "Which controversial novel was originally to have been called 'Tenderness'?",
        "answers": [
            "Wragby Hall",
            "Lady Chatterley's Lover (book)",
            "Lady Chatterly's Lover",
            "Chatterley ban",
            "Oliver Mellors",
            "Connie Chatterley",
            "Lady Chatterley",
            "Constance Chatterley",
            "Lady Chatterly",
            "Short and sharp",
            "Lady Chatterley's Lover",
            "Lady Chatterley\u2019s Lover"
        ],
        "subject": "Daniel Day-Lewis"
    },
    {
        "question": "In which year in the 1930's were Bonnie and Clyde killed?",
        "answers": [
            "one thousand, nine hundred and thirty-four",
            "1934"
        ],
        "subject": "Daniel Day-Lewis"
    },
    {
        "question": "There are two forms of classical Japanese theatre, 'Noh' is mostly spoken, but what name is given to the singing and dancing form?",
        "answers": [
            "\u6b4c\u821e\u4f0e",
            "Kabuky",
            "Kabuki play",
            "Kabuki Theatre",
            "Kabuki",
            "Kabuki theater"
        ],
        "subject": "Daniel Day-Lewis"
    },
    {
        "question": "In Greek mythology, what is Erinys?",
        "answers": [
            "Fury (film)",
            "The Fury",
            "Fury",
            "FURY",
            "Fury (novel)",
            "Fury (disambiguation)",
            "A Fury"
        ],
        "subject": "Daniel Day-Lewis"
    },
    {
        "question": "Which microprocessor was introduced by Intel in 1993?",
        "answers": [
            "Intel Pentium Processor",
            "Pentium (disambiguation)",
            "Pentium processor",
            "Pentium",
            "Pentium brand",
            "Pentium family",
            "Pentium E",
            "Intel Pentium",
            "Pentium (brand)",
            "PENTIUM",
            "Pentium (trademark)"
        ],
        "subject": "Daniel Day-Lewis"
    },
    {
        "question": "Peter Parker alias Spiderman worked for which newspaper?",
        "answers": [
            "DB (comics)",
            "Daily Bugle",
            "The DB",
            "Daily Bugle: Civil War Edition",
            "Front Line (comics)",
            "The Daily Bugle",
            "Daily Bugle Communications",
            "Dexter Bennett"
        ],
        "subject": "Daniel Day-Lewis"
    },
    {
        "question": "In what city is Coney Island located?",
        "answers": [
            "UN/LOCODE:USNYC",
            "NYC, New York",
            "New York city",
            "New York (N.Y.)",
            "New York City, N. Y.",
            "New York City (NY)",
            "City of NY",
            "New Yawk",
            "New York City, United States",
            "New York City, N.Y.",
            "The City So Nice They Named It Twice",
            "New York, US-NY",
            "New york, ny",
            "New York City, USA",
            "New York New York",
            "New Yourk City",
            "N Y (city)",
            "New York City Birth Index",
            "New York, United States of America",
            "The City of New York",
            "N yc",
            "New York, N.Y.",
            "The city of N. Y.",
            "Nueva York",
            "New York (NY)",
            "New York City, N Y",
            "New york new york",
            "N Y City",
            "N. Y. C.",
            "New York CIty",
            "New York City (Ny.)",
            "New York, NY, USA",
            "NYC",
            "NY (city)",
            "City of new yourk",
            "New York City (NYC), USA",
            "New York NY",
            "New York City",
            "New your city",
            "N. Y. (city)",
            "N.Y.C., N.Y.",
            "The Center School (Manhattan)",
            "N Y C, N Y",
            "City of N.Y.",
            "New York, New York, USA",
            "New York City, New York",
            "N. Y., N. Y.",
            "New York Cty",
            "N.Y.C",
            "N.Y.C.",
            "New York (city)",
            "N. Y. C., N. Y.",
            "New York City, New York, United States",
            "N y c",
            "New York, New York",
            "The city of NY",
            "N.Y., N.Y.",
            "New york city",
            "New york City",
            "N. Y. City",
            "New york, New York",
            "New York City, U.S.",
            "City of New York",
            "N Y, N Y",
            "New York (City)",
            "The city of N Y",
            "NY City",
            "City New York",
            "New York City, United States of America",
            "New York City, New York, USA",
            "New York, NY",
            "New York City, NY",
            "NY, NY",
            "City of new york",
            "New york city, new york",
            "N.Y. City",
            "City of N. Y.",
            "Nyc",
            "NYC.gov",
            "The city of N.Y.",
            "Ny c",
            "City That Never Sleeps (city)",
            "New York, New York (State)",
            "New York, N Y",
            "NewYork City",
            "NYC, NY",
            "USNYC",
            "New-York City",
            "Newyorkcity",
            "City of N Y",
            "N.Y. (city)",
            "City of New York, New York",
            "New York, N. Y."
        ],
        "subject": "Daniel Day-Lewis"
    },
    {
        "question": "'Peaches' and 'Trixie Bell' are two of which singer's daughters?",
        "answers": [
            "BOB GELDHOF"
        ],
        "subject": "Daniel Day-Lewis"
    },
    {
        "question": "Where in the human body can you find the 'Olfactory Bulb'?",
        "answers": [
            "The Nose (novel)",
            "The Nose",
            "NOSE",
            "Nose (disambiguation)"
        ],
        "subject": "Daniel Day-Lewis"
    },
    {
        "question": "The Art Nouveau designer Rene Lalique most famously worked in which material?",
        "answers": [
            "Optical glass",
            "Glass sheet",
            "Glass Science",
            "Glass origins",
            "Glass (material)",
            "Optical quality glass",
            "Vitreous state",
            "Crafted glass",
            "Glass",
            "Glass physics",
            "How glass is made",
            "Industrial Glass",
            "Glassy state",
            "Silicate glass",
            "Physics of glass",
            "Glassmaker",
            "Industrial glass",
            "Glassy State",
            "Optical-quality glass",
            "Vitreous materials",
            "Glassy",
            "Glassmaking",
            "Oxide glass",
            "Glass sand",
            "Vitreous Materials"
        ],
        "subject": "Daniel Day-Lewis"
    },
    {
        "question": "Who is the lead singer of the English band \u2018The Specials\u2019?",
        "answers": [
            "Hall, Terry",
            "Terry Hall (disambiguation)",
            "Terry Hall"
        ],
        "subject": "Daniel Day-Lewis"
    },
    {
        "question": "What is the international telephone dialling code for Germany?",
        "answers": [
            "forty-nine",
            "49"
        ],
        "subject": "Daniel Day-Lewis"
    },
    {
        "question": "In which part of the body might one sustain a Pott's Fracture? \\",
        "answers": [
            "Ancle",
            "The ANKLE",
            "Ankles",
            "Articulatio talocruralis",
            "Talocrural joint",
            "Talocrural articulation",
            "Tibiotalar joint",
            "Talocrural",
            "Ankle examination",
            "Ankle-joint",
            "Ankle joint",
            "Ankle",
            "Mortise view"
        ],
        "subject": "Daniel Day-Lewis"
    },
    {
        "question": "What do students at Oxford call their formal academic attire ?",
        "answers": [
            "Academic dress at Oxford University",
            "Academic dress of the university of oxford",
            "Academic dress of Oxford University",
            "SUBFUSC",
            "Sub-fusc",
            "Academic dress of the University of Oxford",
            "Subfusc",
            "Sub fusc"
        ],
        "subject": "Daniel Day-Lewis"
    },
    {
        "question": "Who was the last Catholic monarch to reign over England?",
        "answers": [
            "James II of Ireland",
            "James II (England)",
            "King James VII",
            "James II of England",
            "James Duke Of York",
            "James II of england",
            "King James II",
            "James VII",
            "James VII of Scots",
            "James Stuart, Duke of York",
            "James II Stuart",
            "King James II of England",
            "James II, King of England",
            "James VII/II",
            "James Ii",
            "James VII of the UK",
            "James II (of England)",
            "James VII of Scotland and II of England",
            "King James VII of Scotland",
            "James of York",
            "James the Second",
            "James VII of the United Kingdom",
            "James ii",
            "James II and VII",
            "Jimmy Two",
            "James II & VII",
            "James VII of Scotland",
            "James II",
            "Cultural depictions of James II of England",
            "James II of England, VII of Scotland",
            "James VI of Scotland and II of England",
            "James the Shit",
            "James II of Great Britain",
            "James II of England and VII of Scotland",
            "James VII and II",
            "James, Duke of York",
            "KJII"
        ],
        "subject": "Daniel Day-Lewis"
    },
    {
        "question": "What is the common name of the laryngeal prominence?",
        "answers": [
            "Adams Apple",
            "Prominentia laryngica",
            "Adam's Apple",
            "Adams' apple",
            "Laryngeal protrusion",
            "Adams apple",
            "Prominentia laryngealis",
            "Adem elmas\u0131",
            "Pomum Adami",
            "Adam's apple",
            "Adem elmasi",
            "Prominentia laryngea",
            "Adems apple",
            "Adems Apple",
            "Adem's Apple",
            "Laryngeal prominence",
            "Adem's apple",
            "Laryngeal protuberance",
            "Pomum Adam"
        ],
        "subject": "Daniel Day-Lewis"
    },
    {
        "question": "What gambling game takes its name from French for toad, supposedly from players' hunched positions?",
        "answers": [
            "Hard Eight (craps)",
            "7 come 11",
            "Pass Line",
            "Bank Craps",
            "Don't come",
            "Shooting dice",
            "Crap-shooting",
            "Little dick",
            "Crap-shoot",
            "Baby needs a new pair of shoes",
            "Street craps",
            "Hard Eight(craps)",
            "Pass line",
            "Craps-shooting",
            "Online craps",
            "Hard 4",
            "Craps",
            "Hard 6",
            "Hard 8",
            "Craps (dice game)",
            "Shooting Dice"
        ],
        "subject": "Daniel Day-Lewis"
    }
]